alu.v
// src/alu.v
// Arithmetic Logic Unit (ALU) module

module alu (
    input wire [31:0] op1_i,         // First operand
    input wire [31:0] op2_i,         // Second operand
    input wire  [3:0] alu_op_i,      // ALU operation code (control signal)
    output reg [31:0] alu_result_o,  // ALU result
    output reg        zero_o         // Zero flag (result is 0)
);

// Define ALU operation codes (these are arbitrary, will be determined by Control Unit)
// You can use parameter for better readability later, or localparam inside alu.v
localparam ALU_ADD  = 4'b0000; // ADD
localparam ALU_SUB  = 4'b0001; // SUB
localparam ALU_AND  = 4'b0010; // AND
localparam ALU_OR   = 4'b0011; // OR
localparam ALU_XOR  = 4'b0100; // XOR
localparam ALU_SLL  = 4'b0101; // Shift Left Logical
localparam ALU_SRL  = 4'b0110; // Shift Right Logical
localparam ALU_SRA  = 4'b0111; // Shift Right Arithmetic
localparam ALU_SLT  = 4'b1000; // Set Less Than (signed)
localparam ALU_SLTU = 4'b1001; // Set Less Than Unsigned
localparam ALU_COPY_B = 4'b1111; // For cases where op2 is just passed through (e.g., LUI, JAL, etc.)

// ALU combinational logic
always @(*) begin
    alu_result_o = 32'hX; // Default to X (unknown) for unhandled operations
    zero_o = 1'b0;       // Default zero flag to 0

    case (alu_op_i)
        ALU_ADD:    alu_result_o = op1_i + op2_i;
        ALU_SUB:    alu_result_o = op1_i - op2_i;
        ALU_AND:    alu_result_o = op1_i & op2_i;
        ALU_OR:     alu_result_o = op1_i | op2_i;
        ALU_XOR:    alu_result_o = op1_i ^ op2_i;
        ALU_SLL:    alu_result_o = op1_i << op2_i[4:0]; // Shift amount is 5 bits
        ALU_SRL:    alu_result_o = op1_i >> op2_i[4:0];
        ALU_SRA:    alu_result_o = $signed(op1_i) >>> op2_i[4:0]; // Signed right shift
        ALU_SLT:    alu_result_o = ($signed(op1_i) < $signed(op2_i)) ? 32'h1 : 32'h0;
        ALU_SLTU:   alu_result_o = (op1_i < op2_i) ? 32'h1 : 32'h0;
        ALU_COPY_B: alu_result_o = op2_i; // Pass through op2 (e.g., for AUIPC/LUI where ALU just needs immediate)
        default:    alu_result_o = 32'hX; // Handle unexpected op_codes
    endcase

    // Set zero flag
    if (alu_result_o == 32'h0) begin
        zero_o = 1'b1;
    end
end

endmodule

alu_tb.v
// tb/alu_tb.v
// Testbench for ALU module

`timescale 1ns/1ns

module alu_tb;

    // --- Testbench Signals ---
    reg  [31:0] op1_i;
    reg  [31:0] op2_i;
    reg  [3:0]  alu_op_i;
    wire [31:0] alu_result_o;
    wire        zero_o;

    // --- Instantiate the Device Under Test (DUT) ---
    alu DUT (
        .op1_i        (op1_i),
        .op2_i        (op2_i),
        .alu_op_i     (alu_op_i),
        .alu_result_o (alu_result_o),
        .zero_o       (zero_o)
    );

    // Define ALU operation codes (must match alu.v)
    localparam ALU_ADD  = 4'b0000;
    localparam ALU_SUB  = 4'b0001;
    localparam ALU_AND  = 4'b0010;
    localparam ALU_OR   = 4'b0011;
    localparam ALU_XOR  = 4'b0100;
    localparam ALU_SLL  = 4'b0101;
    localparam ALU_SRL  = 4'b0110;
    localparam ALU_SRA  = 4'b0111;
    localparam ALU_SLT  = 4'b1000;
    localparam ALU_SLTU = 4'b1001;
    localparam ALU_COPY_B = 4'b1111;

    // --- Initial Block (Test Scenario) ---
    initial begin
        // Dump waveforms
        $dumpfile("sim/alu_tb.vcd");
        $dumpvars(0, alu_tb);

        // Initialize inputs
        op1_i = 32'h0;
        op2_i = 32'h0;
        alu_op_i = ALU_ADD; // Start with ADD

        // --- Test Sequence ---

        #10; // Wait for initial propagation

        // 1. ADD
        op1_i = 32'd10;
        op2_i = 32'd5;
        alu_op_i = ALU_ADD;
        #10;
        $display("Time %0t: %h + %h = %h, Zero = %b", $time, op1_i, op2_i, alu_result_o, zero_o);
        // Expected: 10 + 5 = F (0x0F), Zero = 0

        // 2. SUB (result is zero)
        op1_i = 32'd20;
        op2_i = 32'd20;
        alu_op_i = ALU_SUB;
        #10;
        $display("Time %0t: %h - %h = %h, Zero = %b", $time, op1_i, op2_i, alu_result_o, zero_o);
        // Expected: 20 - 20 = 0, Zero = 1

        // 3. AND
        op1_i = 32'hF0F0;
        op2_i = 32'h0F0F;
        alu_op_i = ALU_AND;
        #10;
        $display("Time %0t: %h & %h = %h, Zero = %b", $time, op1_i, op2_i, alu_result_o, zero_o);
        // Expected: F0F0 & 0F0F = 0000, Zero = 1

        // 4. OR
        op1_i = 32'hF0F0;
        op2_i = 32'h0F0F;
        alu_op_i = ALU_OR;
        #10;
        $display("Time %0t: %h | %h = %h, Zero = %b", $time, op1_i, op2_i, alu_result_o, zero_o);
        // Expected: F0F0 | 0F0F = FFFF, Zero = 0

        // 5. XOR
        op1_i = 32'hA5A5A5A5;
        op2_i = 32'h5A5A5A5A;
        alu_op_i = ALU_XOR;
        #10;
        $display("Time %0t: %h ^ %h = %h, Zero = %b", $time, op1_i, op2_i, alu_result_o, zero_o);
        // Expected: A5A5A5A5 ^ 5A5A5A5A = FFFFFFFF, Zero = 0

        // 6. SLL (Shift Left Logical)
        op1_i = 32'h0000000F; // 15
        op2_i = 32'd2;        // Shift by 2
        alu_op_i = ALU_SLL;
        #10;
        $display("Time %0t: %h << %d = %h, Zero = %b", $time, op1_i, op2_i, alu_result_o, zero_o);
        // Expected: 0000000F << 2 = 0000003C (60), Zero = 0

        // 7. SRL (Shift Right Logical)
        op1_i = 32'h80000000;
        op2_i = 32'd1;
        alu_op_i = ALU_SRL;
        #10;
        $display("Time %0t: %h >> %d = %h, Zero = %b", $time, op1_i, op2_i, alu_result_o, zero_o);
        // Expected: 80000000 >> 1 = 40000000, Zero = 0

        // 8. SRA (Shift Right Arithmetic - preserves sign)
        op1_i = 32'hFFFFFFFE; // -2 signed
        op2_i = 32'd1;
        alu_op_i = ALU_SRA;
        #10;
        $display("Time %0t: %h >>> %d = %h, Zero = %b", $time, op1_i, op2_i, alu_result_o, zero_o);
        // Expected: FFFFFFFE (-2) >>> 1 = FFFFFFFF (-1), Zero = 0

        // 9. SLT (Set Less Than - signed)
        op1_i = 32'd5;
        op2_i = 32'd10;
        alu_op_i = ALU_SLT;
        #10;
        $display("Time %0t: %d SLT %d = %h, Zero = %b", $time, $signed(op1_i), $signed(op2_i), alu_result_o, zero_o);
        // Expected: 5 < 10 = 1, Zero = 0

        // 10. SLT (Set Less Than - signed) - false case
        op1_i = 32'd10;
        op2_i = 32'd5;
        alu_op_i = ALU_SLT;
        #10;
        $display("Time %0t: %d SLT %d = %h, Zero = %b", $time, $signed(op1_i), $signed(op2_i), alu_result_o, zero_o);
        // Expected: 10 < 5 = 0, Zero = 1

        // 11. SLT (signed) - negative numbers
        op1_i = 32'hFFFFFFFF; // -1
        op2_i = 32'd0;
        alu_op_i = ALU_SLT;
        #10;
        $display("Time %0t: %d SLT %d = %h, Zero = %b", $time, $signed(op1_i), $signed(op2_i), alu_result_o, zero_o);
        // Expected: -1 < 0 = 1, Zero = 0

        // 12. SLTU (Set Less Than Unsigned)
        op1_i = 32'hFFFFFFFF; // unsigned max
        op2_i = 32'd0;
        alu_op_i = ALU_SLTU;
        #10;
        $display("Time %0t: %h SLTU %h = %h, Zero = %b", $time, op1_i, op2_i, alu_result_o, zero_o);
        // Expected: FFFFFFFF (large) < 0 (small) = 0, Zero = 1

        // 13. SLTU (unsigned) - true case
        op1_i = 32'd10;
        op2_i = 32'hFFFFFFFF;
        alu_op_i = ALU_SLTU;
        #10;
        $display("Time %0t: %h SLTU %h = %h, Zero = %b", $time, op1_i, op2_i, alu_result_o, zero_o);
        // Expected: 10 (small) < FFFFFFFF (large) = 1, Zero = 0

        // 14. ALU_COPY_B
        op1_i = 32'hAAAAAAAA; // irrelevant for COPY_B
        op2_i = 32'hBBBBBBBB;
        alu_op_i = ALU_COPY_B;
        #10;
        $display("Time %0t: COPY_B %h = %h, Zero = %b", $time, op2_i, alu_result_o, zero_o);
        // Expected: BBBBBBBB, Zero = 0

        // 15. Default (unhandled operation)
        alu_op_i = 4'b1010; // Unknown op code
        #10;
        $display("Time %0t: Default op: Result = %h, Zero = %b", $time, alu_result_o, zero_o);
        // Expected: XXXXXXXX (or some other uninitialized value), Zero = 0 or X

        #20 $finish; // End simulation
    end

endmodule

alu_tb.vcd
$date
	Mon Jul 28 13:19:31 2025
$end
$version
	Icarus Verilog
$end
$timescale
	1ns
$end
$scope module alu_tb $end
$var wire 1 ! zero_o $end
$var wire 32 " alu_result_o [31:0] $end
$var parameter 4 # ALU_ADD $end
$var parameter 4 $ ALU_AND $end
$var parameter 4 % ALU_COPY_B $end
$var parameter 4 & ALU_OR $end
$var parameter 4 ' ALU_SLL $end
$var parameter 4 ( ALU_SLT $end
$var parameter 4 ) ALU_SLTU $end
$var parameter 4 * ALU_SRA $end
$var parameter 4 + ALU_SRL $end
$var parameter 4 , ALU_SUB $end
$var parameter 4 - ALU_XOR $end
$var reg 4 . alu_op_i [3:0] $end
$var reg 32 / op1_i [31:0] $end
$var reg 32 0 op2_i [31:0] $end
$scope module DUT $end
$var wire 4 1 alu_op_i [3:0] $end
$var wire 32 2 op1_i [31:0] $end
$var wire 32 3 op2_i [31:0] $end
$var parameter 4 4 ALU_ADD $end
$var parameter 4 5 ALU_AND $end
$var parameter 4 6 ALU_COPY_B $end
$var parameter 4 7 ALU_OR $end
$var parameter 4 8 ALU_SLL $end
$var parameter 4 9 ALU_SLT $end
$var parameter 4 : ALU_SLTU $end
$var parameter 4 ; ALU_SRA $end
$var parameter 4 < ALU_SRL $end
$var parameter 4 = ALU_SUB $end
$var parameter 4 > ALU_XOR $end
$var reg 32 ? alu_result_o [31:0] $end
$var reg 1 ! zero_o $end
$upscope $end
$upscope $end
$enddefinitions $end
$comment Show the parameter values. $end
$dumpall
b100 >
b1 =
b110 <
b111 ;
b1001 :
b1000 9
b101 8
b11 7
b1111 6
b10 5
b0 4
b100 -
b1 ,
b110 +
b111 *
b1001 )
b1000 (
b101 '
b11 &
b1111 %
b10 $
b0 #
$end
#0
$dumpvars
b0 ?
b0 3
b0 2
b0 1
b0 0
b0 /
b0 .
b0 "
1!
$end
#10
0!
b1111 "
b1111 ?
b101 0
b101 3
b1010 /
b1010 2
#20
1!
b0 "
b0 ?
b1 .
b1 1
b10100 0
b10100 3
b10100 /
b10100 2
#30
1!
b0 "
b0 ?
b10 .
b10 1
b111100001111 0
b111100001111 3
b1111000011110000 /
b1111000011110000 2
#40
0!
b1111111111111111 "
b1111111111111111 ?
b11 .
b11 1
#50
b11111111111111111111111111111111 "
b11111111111111111111111111111111 ?
b100 .
b100 1
b1011010010110100101101001011010 0
b1011010010110100101101001011010 3
b10100101101001011010010110100101 /
b10100101101001011010010110100101 2
#60
b111100 "
b111100 ?
b101 .
b101 1
b10 0
b10 3
b1111 /
b1111 2
#70
b1000000000000000000000000000000 "
b1000000000000000000000000000000 ?
b110 .
b110 1
b1 0
b1 3
b10000000000000000000000000000000 /
b10000000000000000000000000000000 2
#80
b11111111111111111111111111111111 "
b11111111111111111111111111111111 ?
b111 .
b111 1
b11111111111111111111111111111110 /
b11111111111111111111111111111110 2
#90
b1 "
b1 ?
b1000 .
b1000 1
b1010 0
b1010 3
b101 /
b101 2
#100
1!
b0 "
b0 ?
b101 0
b101 3
b1010 /
b1010 2
#110
0!
b1 "
b1 ?
b0 0
b0 3
b11111111111111111111111111111111 /
b11111111111111111111111111111111 2
#120
1!
b0 "
b0 ?
b1001 .
b1001 1
#130
0!
b1 "
b1 ?
b11111111111111111111111111111111 0
b11111111111111111111111111111111 3
b1010 /
b1010 2
#140
b10111011101110111011101110111011 "
b10111011101110111011101110111011 ?
b1111 .
b1111 1
b10111011101110111011101110111011 0
b10111011101110111011101110111011 3
b10101010101010101010101010101010 /
b10101010101010101010101010101010 2
#150
bx "
bx ?
b1010 .
b1010 1
