immediate_generator.v
// src/immediate_generator.v
// Immediate Generator module - FINAL STRUCTURAL CORRECTION (Verilog-2001)

module immediate_generator (
    input wire [31:0] instruction_i, // The 32-bit instruction
    output reg [31:0] imm_o         // The 32-bit sign-extended immediate value
);

// Define instruction opcode types
localparam OPCODE_LUI    = 7'b0110111;
localparam OPCODE_AUIPC  = 7'b0010111;
localparam OPCODE_JAL    = 7'b1101111; // J-type
localparam OPCODE_JALR   = 7'b1100111; // I-type
localparam OPCODE_BRANCH = 7'b1100011; // B-type
localparam OPCODE_LOAD   = 7'b0000011; // I-type
localparam OPCODE_STORE  = 7'b0100011; // S-type
localparam OPCODE_IMM    = 7'b0010011; // I-type (ADDI, SLTI, ANDI, etc.)

// Internal WIRES for raw immediate segments extracted from instruction_i
// These are declared at module level and assigned using continuous assignments
wire [11:0] i_imm_11_0_raw;
wire [6:0]  s_imm_11_5_raw;
wire [4:0]  s_imm_4_0_raw;

wire [12:0] b_imm_raw; // Raw 13-bit B-type immediate, before sign-extension
wire [20:0] j_imm_raw; // Raw 21-bit J-type immediate, before sign-extension
wire [11:0] s_imm_val; // Raw 12-bit S-type immediate (combined)

// Assign raw bits from instruction_i using continuous assignments (`assign` statements)
// These assignments happen concurrently, outside of any 'always' blocks
assign i_imm_11_0_raw   = instruction_i[31:20];
assign s_imm_11_5_raw   = instruction_i[31:25];
assign s_imm_4_0_raw    = instruction_i[11:7];

// B-type Raw Immediate Reassembly (13 bits)
// {imm[12], imm[11], imm[10:5], imm[4:1], imm[0]}
// From instr: {instr[31], instr[7], instr[30:25], instr[11:8], 1'b0}
assign b_imm_raw = {instruction_i[31],    // imm[12]
                     instruction_i[7],     // imm[11]
                     instruction_i[30:25], // imm[10:5]
                     instruction_i[11:8],  // imm[4:1]
                     1'b0};                // imm[0] is always 0

// J-type Raw Immediate Reassembly (21 bits)
// {imm[20], imm[19:12], imm[11], imm[10:1], imm[0]}
// From instr: {instr[31], instr[19:12], instr[20], instr[30:21], 1'b0}
assign j_imm_raw = {instruction_i[31],     // imm[20]
                     instruction_i[19:12], // imm[19:12]
                     instruction_i[20],    // imm[11]
                     instruction_i[30:21], // imm[10:1]
                     1'b0};                 // imm[0] is always 0

// S-type Raw Immediate Reassembly (12 bits)
assign s_imm_val = {s_imm_11_5_raw, s_imm_4_0_raw};


// Main combinational logic to select and sign-extend the immediate
// This 'always @(*)' block assigns to 'imm_o' (a reg type)
wire [6:0] opcode = instruction_i[6:0]; // Opcode is just a slice of instruction_i

always @(*) begin
    imm_o = 32'hX; // Default output for unhandled/R-type

    case (opcode) // Use 'opcode' wire, which is derived from instruction_i
        OPCODE_LUI, OPCODE_AUIPC: begin
            // U-type: imm[31:12] = instruction_i[31:12], imm[11:0] = 0
            imm_o = {instruction_i[31:12], 12'b0};
        end
        OPCODE_JAL: begin
            // J-type: Sign-extend j_imm_raw[20]
            imm_o = {{11{j_imm_raw[20]}}, j_imm_raw}; // 11 sign bits + 21-bit raw immediate
        end
        OPCODE_JALR, OPCODE_LOAD, OPCODE_IMM: begin
            // I-type: Sign-extend i_imm_11_0_raw[11]
            imm_o = {{20{i_imm_11_0_raw[11]}}, i_imm_11_0_raw}; // 20 sign bits + 12-bit raw immediate
        end
        OPCODE_BRANCH: begin
            // B-type: Sign-extend b_imm_raw[12]
            imm_o = {{19{b_imm_raw[12]}}, b_imm_raw}; // 19 sign bits + 13-bit raw immediate
        end
        OPCODE_STORE: begin
            // S-type: Sign-extend s_imm_val[11]
            imm_o = {{20{s_imm_val[11]}}, s_imm_val}; // 20 sign bits + 12-bit raw immediate
        end
        default: begin
            imm_o = 32'hX;
        end
    endcase
end

endmodule

immediate_generator_tb.v
`timescale 1ns / 1ps

module immediate_generator_tb;

  // Inputs
  reg [31:0] instruction_i;
  wire [31:0] imm_o;

  // Instantiate the Unit Under Test (UUT)
  immediate_generator dut (
    .instruction_i(instruction_i),
    .imm_o(imm_o)
  );

  // Task to test a single instruction
  task test_imm;
    input [31:0] instr_in;
    input [31:0] expected_imm;
    input [255:0] type;
    begin
      instruction_i = instr_in;
      #10;
      $display("Time %0t: %s: Instr %h, Imm %h, Expected %h",
               $time, type, instruction_i, imm_o, expected_imm);
      if (imm_o !== expected_imm) begin
        $display("ERROR: Immediate mismatch for %s", type);
        $finish;
      end
    end
  endtask

  initial begin
    // I-type: ADDI
    test_imm(32'h00100093, 32'h00000001, "I-type (ADDI)");
    test_imm(32'hfff00093, 32'hffffffff, "I-type (ADDI)");

    // S-type: SW
    test_imm(32'h001080a3, 32'h00000001, "S-type (SW)");
    test_imm(32'hfff08fa3, 32'hffffffff, "S-type (SW)");

    // B-type: BEQ
    test_imm(32'h00208663, 32'h0000000c, "B-type (BEQ)");
    test_imm(32'hffe08663, 32'hfffff7ec, "B-type (BEQ)");

    // U-type: LUI
    test_imm(32'h123450b7, 32'h12345000, "U-type (LUI)");

    // J-type: JAL
    test_imm(32'h0080006f, 32'h00000008, "J-type (JAL)");
    test_imm(32'hfff0006f, 32'hfff00ffe, "J-type (JAL)");

    $finish;
  end

endmodule

immediate_generator_tb.vcd
$date
	Tue Jul 29 04:37:21 2025
$end
$version
	Icarus Verilog
$end
$timescale
	1ps
$end
$scope module immediate_generator_tb $end
$var wire 32 ! imm_o [31:0] $end
$var reg 32 " instruction_i [31:0] $end
$scope module dut $end
$var wire 32 # instruction_i [31:0] $end
$var wire 12 $ s_imm_val [11:0] $end
$var wire 5 % s_imm_4_0_raw [4:0] $end
$var wire 7 & s_imm_11_5_raw [6:0] $end
$var wire 7 ' opcode [6:0] $end
$var wire 21 ( j_imm_raw [20:0] $end
$var wire 12 ) i_imm_11_0_raw [11:0] $end
$var wire 13 * b_imm_raw [12:0] $end
$var parameter 7 + OPCODE_AUIPC $end
$var parameter 7 , OPCODE_BRANCH $end
$var parameter 7 - OPCODE_IMM $end
$var parameter 7 . OPCODE_JAL $end
$var parameter 7 / OPCODE_JALR $end
$var parameter 7 0 OPCODE_LOAD $end
$var parameter 7 1 OPCODE_LUI $end
$var parameter 7 2 OPCODE_STORE $end
$var reg 32 3 imm_o [31:0] $end
$upscope $end
$upscope $end
$enddefinitions $end
$comment Show the parameter values. $end
$dumpall
b100011 2
b110111 1
b11 0
b1100111 /
b1101111 .
b10011 -
b1100011 ,
b10111 +
$end
#0
$dumpvars
b1 3
b100000000000 *
b1 )
b100000000000 (
b10011 '
b0 &
b1 %
b1 $
b100000000000010010011 #
b100000000000010010011 "
b1 !
$end
#10000
b11111111111111111111111111111111 !
b11111111111111111111111111111111 3
b111111111111 )
b111111100001 $
b1111111 &
b1111111100000 *
b100000000111111111110 (
b11111111111100000000000010010011 "
b11111111111100000000000010010011 #
#20000
b1 !
b1 3
b1 )
b1 $
b0 &
b100000000000 *
b1000100000000000 (
b100011 '
b100001000000010100011 "
b100001000000010100011 #
#30000
b11111111111111111111111111111111 !
b11111111111111111111111111111111 3
b111111111111 )
b1111111 &
b111111111111 $
b11111 %
b1111111111110 *
b100001000111111111110 (
b11111111111100001000111110100011 "
b11111111111100001000111110100011 #
#40000
b1100 !
b1100 3
b10 )
b0 &
b1100 $
b1100 %
b1100 *
b1000000000000010 (
b1100011 '
b1000001000011001100011 "
b1000001000011001100011 #
#50000
b11111111111111111111011111101100 !
b11111111111111111111011111101100 3
b111111111110 )
b111111101100 $
b1111111 &
b1011111101100 *
b100001000011111111110 (
b11111111111000001000011001100011 "
b11111111111000001000011001100011 #
#60000
b10010001101000101000000000000 !
b10010001101000101000000000000 3
b100100011 )
b1001 &
b100100001 $
b1 %
b100100100000 *
b1000101100100100010 (
b110111 '
b10010001101000101000010110111 "
b10010001101000101000010110111 #
#70000
b1000 !
b1000 3
b1000 )
b0 &
b0 $
b0 %
b0 *
b1000 (
b1101111 '
b100000000000000001101111 "
b100000000000000001101111 #
#80000
b11111111111100000000111111111110 !
b11111111111100000000111111111110 3
b111111111111 )
b111111100000 $
b1111111 &
b1011111100000 *
b100000000111111111110 (
b11111111111100000000000001101111 "
b11111111111100000000000001101111 #
