pc_reg.v
// src/pc_reg.v
// Program Counter (PC) module

module pc_reg (
    input wire        clk,          // Clock signal
    input wire        rst_n,        // Asynchronous reset (active low)
    input wire [31:0] pc_next_i,    // Next PC value input
    input wire        pc_write_en_i,// Enable to update PC (for normal increment or branch/jump)
    output reg [31:0] pc_o          // Current PC value output
);

// PC register update logic
always @(posedge clk or negedge rst_n) begin
    if (~rst_n) begin // Asynchronous active-low reset
        pc_o <= 32'h00000000; // Reset PC to 0
    end else if (pc_write_en_i) begin // Update PC only when enabled
        pc_o <= pc_next_i;
    end
end

endmodule

pc_reg_tb.v
// tb/pc_reg_tb.v
// Testbench for Program Counter (PC) module

`timescale 1ns/1ns // Define time units for simulation

module pc_reg_tb;

    // --- Testbench Signals (wires and regs for connecting to DUT) ---
    reg         clk;
    reg         rst_n;
    reg  [31:0] pc_next_i;
    reg         pc_write_en_i;
    wire [31:0] pc_o;

    // --- Instantiate the Device Under Test (DUT) ---
    pc_reg DUT (
        .clk            (clk),
        .rst_n          (rst_n),
        .pc_next_i      (pc_next_i),
        .pc_write_en_i  (pc_write_en_i),
        .pc_o           (pc_o)
    );

    // --- Clock Generation ---
    // Create a clock with a period of 10ns (frequency 100 MHz)
    always #5 clk = ~clk; // Toggle clk every 5ns (half period)

    // --- Initial Block (Test Scenario) ---
    initial begin
        // Initialize signals
        clk = 0;
        rst_n = 0; // Assert reset
        pc_next_i = 32'h00000000;
        pc_write_en_i = 0;

        // Dump waveforms for GTKWave
        $dumpfile("sim/pc_reg_tb.vcd"); // Where to save the waveform data
        $dumpvars(0, pc_reg_tb);       // Dump all signals in this module and its sub-modules

        // --- Test Sequence ---

        #10 rst_n = 1; // De-assert reset after 10ns

        // 1. Initial PC value after reset (should be 0x0)
        // Wait for a clock cycle to observe reset output
        #10;
        $display("Time %0t: PC after reset = %h", $time, pc_o);
        // Expected: 0x0

        // 2. Normal PC increment (PC = PC + 4)
        // Simulate fetching instruction at 0x00000000
        pc_next_i = 32'h00000004; // Set next PC to 4 (current_pc + 4)
        pc_write_en_i = 1;
        #10; // Wait for one clock cycle
        $display("Time %0t: PC after increment 1 = %h", $time, pc_o);
        // Expected: 0x00000004

        // 3. Another normal increment
        pc_next_i = 32'h00000008; // Set next PC to 8
        #10;
        $display("Time %0t: PC after increment 2 = %h", $time, pc_o);
        // Expected: 0x00000008

        // 4. Load a new PC value (e.g., for a jump or branch)
        pc_next_i = 32'h00000100; // Jump to address 0x100
        #10;
        $display("Time %0t: PC after jump = %h", $time, pc_o);
        // Expected: 0x00000100

        // 5. Test pc_write_en_i (stalling PC)
        pc_write_en_i = 0;       // Disable PC write
        pc_next_i = 32'h00000104; // Even if next is 0x104
        #10;
        $display("Time %0t: PC after attempted write (disabled) = %h", $time, pc_o);
        // Expected: 0x00000100 (should not change)

        // 6. Re-enable write and see it update
        pc_write_en_i = 1;
        #10;
        $display("Time %0t: PC after re-enabled write = %h", $time, pc_o);
        // Expected: 0x00000104

        // --- End of Simulation ---
        #20 $finish; // End simulation after 20 more ns
    end

endmodule

pc_reg_tb.vcd
$date
	Mon Jul 28 06:59:04 2025
$end
$version
	Icarus Verilog
$end
$timescale
	1ns
$end
$scope module pc_reg_tb $end
$var wire 32 ! pc_o [31:0] $end
$var reg 1 " clk $end
$var reg 32 # pc_next_i [31:0] $end
$var reg 1 $ pc_write_en_i $end
$var reg 1 % rst_n $end
$scope module DUT $end
$var wire 1 " clk $end
$var wire 32 & pc_next_i [31:0] $end
$var wire 1 $ pc_write_en_i $end
$var wire 1 % rst_n $end
$var reg 32 ' pc_o [31:0] $end
$upscope $end
$upscope $end
$enddefinitions $end
$comment Show the parameter values. $end
$dumpall
$end
#0
$dumpvars
b0 '
b0 &
0%
0$
b0 #
0"
b0 !
$end
#5
1"
#10
0"
1%
#15
1"
#20
0"
1$
b100 #
b100 &
#25
b100 !
b100 '
1"
#30
0"
b1000 #
b1000 &
#35
b1000 !
b1000 '
1"
#40
0"
b100000000 #
b100000000 &
#45
b100000000 !
b100000000 '
1"
#50
0"
b100000100 #
b100000100 &
0$
#55
1"
#60
0"
1$
#65
b100000100 !
b100000100 '
1"
